{
  "track": "Donington Park MAY 2025 TEST",
  "variant": "National MAY 2025 TEST",
  "car": "Dallara F309",
  "month": "May",
  "year": 2025,
  "results": [
    {
      "position": 1,
      "driver": "MAY 2025 TEST fastest",
      "laptime": "1:12.287",
      "sector1": "23.581",
      "sector2": "20.018",
      "sector3": "28.688",
      "timestamp": "25-05-29 20:07"
    },
    {
      "position": 2,
      "driver": "MAY 2025 TEST second",
      "laptime": "1:13.001",
      "sector1": "23.782",
      "sector2": "20.300",
      "sector3": "28.919",
      "timestamp": "25-05-29 20:45"
    },
    {
      "position": 2,
      "driver": "MAY 2025 TEST third",
      "laptime": "1:13.100",
      "sector1": "23.800",
      "sector2": "20.300",
      "sector3": "29.000",
      "timestamp": "25-05-29 20:41"
    }
  ]
}
