[
  {
    "Position": "14",
    "Name": "Ieuan Rees",
    "SteamID": "76561198207011993",
    "LapTime": "1:45.320",
    "Sector1": "35.194",
    "Sector2": "34.379",
    "Sector3": "35.747",
    "Gap": "+7.216",
    "Car": "MetalMoro AJR Gen2 Honda",
    "Date": "25-07-01 19:51",
    "Flags": "W|-|A|T|C"
  },
  {
    "Position": "22",
    "Name": "Chris Rees",
    "SteamID": "76561197971749679",
    "LapTime": "1:57.840",
    "Sector1": "39.165",
    "Sector2": "39.294",
    "Sector3": "39.381",
    "Gap": "+19.736",
    "Car": "MetalMoro AJR Gen2 Honda",
    "Date": "25-07-01 21:12",
    "Flags": "W|+|A|T"
  }
]